Algebra_Linear/Matriz.py
Algebra_Linear/Vetor.py
Algebra_Linear/__init__.py
Algebra_Linear-0.0.1.dist-info/METADATA
Algebra_Linear-0.0.1.dist-info/WHEEL
Algebra_Linear-0.0.1.dist-info/top_level.txt
Algebra_Linear-0.0.1.dist-info/RECORD
